pypisd/__init__.py
pypisd/main.py
pypisd-0.1.3.dist-info/entry_points.txt
pypisd-0.1.3.dist-info/LICENSE
pypisd-0.1.3.dist-info/WHEEL
pypisd-0.1.3.dist-info/METADATA
pypisd-0.1.3.dist-info/RECORD
