Metadata-Version: 2.1
Name: pypisd
Version: 0.1.3
Summary: CLI tool to fetch source distribution url links from https://pypi.org for a given python package and its version.
Home-page: https://github.com/fegoa89/pypisd
License: MIT
Keywords: pypisd,source distribution link,library download link
Author: Fernando
Author-email: fegoa89@gmail.com
Requires-Python: >=3.7,<4.0
Classifier: License :: OSI Approved :: MIT License
Classifier: Programming Language :: Python :: 3
Classifier: Programming Language :: Python :: 3.10
Classifier: Programming Language :: Python :: 3.7
Classifier: Programming Language :: Python :: 3.8
Classifier: Programming Language :: Python :: 3.9
Requires-Dist: bs4 (>=0.0.1,<0.0.2)
Requires-Dist: requests (>=2.27.1,<3.0.0)
Requires-Dist: toml (>=0.10.2,<0.11.0)
Project-URL: Repository, https://github.com/fegoa89/pypisd
